{"BL01": {"@CID": "2", "@Cart1L": "1", "@Cart1W": "3.129", "@Cart2L": "1", "@Cart2W": "3.124", "@Cart3L": "1", "@Cart3W": "3.173", "@Cart4L": "1", "@Cart4W": "3.017", "@Cart5L": "1", "@Cart5W": "3.227", "@Cart6L": "1", "@Cart6W": "3.188", "@StationID": "BL01", "@TrainNumber": "218", "@updateTime": "2020-07-13 20:05:19"}, "BL02": {"@CID": "2", "@Cart1L": "1", "@Cart1W": "3.124", "@Cart2L": "1", "@Cart2W": "3.134", "@Cart3L": "1", "@Cart3W": "3.149", "@Cart4L": "1", "@Cart4W": "3.085", "@Cart5L": "1", "@Cart5W": "3.266", "@Cart6L": "1", "@Cart6W": "3.207", "@StationID": "BL02", "@TrainNumber": "218", "@updateTime": "2020-07-13 20:08:26"}, "BL03": {"@CID": "2", "@Cart1L": "1", "@Cart1W": "3.159", "@Cart2L": "1", "@Cart2W": "3.154", "@Cart3L": "1", "@Cart3W": "3.188", "@Cart4L": "1", "@Cart4W": "3.105", "@Cart5L": "1", "@Cart5W": "3.276", "@Cart6L": "1", "@Cart6W": "3.188", "@StationID": "BL03", "@TrainNumber": "218", "@updateTime": "2020-07-13 20:10:29"}, "BL04": {"@CID": "2", "@Cart1L": "1", "@Cart1W": "3.207", "@Cart2L": "1", "@Cart2W": "3.203", "@Cart3L": "1", "@Cart3W": "3.207", "@Cart4L": "1", "@Cart4W": "3.124", "@Cart5L": "1", "@Cart5W": "3.315", "@Cart6L": "1", "@Cart6W": "3.193", "@StationID": "BL04", "@TrainNumber": "218", "@updateTime": "2020-07-13 20:12:39"}, "BL05": {"@CID": "2", "@Cart1L": "1", "@Cart1W": "3.168", "@Cart2L": "1", "@Cart2W": "3.222", "@Cart3L": "1", "@Cart3W": "3.237", "@Cart4L": "1", "@Cart4W": "3.12", "@Cart5L": "1", "@Cart5W": "3.31", "@Cart6L": "1", "@Cart6W": "3.198", "@StationID": "BL05", "@TrainNumber": "218", "@updateTime": "2020-07-13 20:15:32"}, "BL06": {"@CID": "2", "@Cart1L": "1", "@Cart1W": "3.188", "@Cart2L": "1", "@Cart2W": "3.256", "@Cart3L": "1", "@Cart3W": "3.325", "@Cart4L": "1", "@Cart4W": "3.227", "@Cart5L": "1", "@Cart5W": "3.349", "@Cart6L": "1", "@Cart6W": "3.217", "@StationID": "BL06", "@TrainNumber": "218", "@updateTime": "2020-07-13 20:17:48"}, "BL07": {"@CID": "2", "@Cart1L": "1", "@Cart1W": "3.193", "@Cart2L": "1", "@Cart2W": "3.369", "@Cart3L": "1", "@Cart3W": "3.388", "@Cart4L": "1", "@Cart4W": "3.207", "@Cart5L": "1", "@Cart5W": "3.349", "@Cart6L": "1", "@Cart6W": "3.281", "@StationID": "BL07", "@TrainNumber": "218", "@updateTime": "2020-07-13 20:19:18"}, "BL08": {"@CID": "2", "@Cart1L": "1", "@Cart1W": "3.256", "@Cart2L": "1", "@Cart2W": "3.383", "@Cart3L": "1", "@Cart3W": "3.383", "@Cart4L": "1", "@Cart4W": "3.198", "@Cart5L": "1", "@Cart5W": "3.378", "@Cart6L": "1", "@Cart6W": "3.29", "@StationID": "BL08", "@TrainNumber": "218", "@updateTime": "2020-07-13 20:21:31"}, "BL09": {"@CID": "2", "@Cart1L": "1", "@Cart1W": "3.251", "@Cart2L": "1", "@Cart2W": "3.369", "@Cart3L": "1", "@Cart3W": "3.354", "@Cart4L": "1", "@Cart4W": "3.178", "@Cart5L": "1", "@Cart5W": "3.383", "@Cart6L": "1", "@Cart6W": "3.286", "@StationID": "BL09", "@TrainNumber": "218", "@updateTime": "2020-07-13 20:23:18"}, "BL10": {"@CID": "2", "@Cart1L": "1", "@Cart1W": "3.295", "@Cart2L": "1", "@Cart2W": "3.383", "@Cart3L": "1", "@Cart3W": "3.344", "@Cart4L": "1", "@Cart4W": "3.247", "@Cart5L": "1", "@Cart5W": "3.393", "@Cart6L": "1", "@Cart6W": "3.286", "@StationID": "BL10", "@TrainNumber": "218", "@updateTime": "2020-07-13 20:26:59"}, "BL11": {"@CID": "2", "@Cart1L": "1", "@Cart1W": "3.237", "@Cart2L": "1", "@Cart2W": "3.417", "@Cart3L": "1", "@Cart3W": "3.31", "@Cart4L": "1", "@Cart4W": "3.212", "@Cart5L": "1", "@Cart5W": "3.373", "@Cart6L": "1", "@Cart6W": "3.256", "@StationID": "BL11", "@TrainNumber": "218", "@updateTime": "2020-07-13 20:29:34"}, "BL12": {"@CID": "2", "@Cart1L": "1", "@Cart1W": "3.305", "@Cart2L": "1", "@Cart2W": "3.491", "@Cart3L": "1", "@Cart3W": "3.33", "@Cart4L": "1", "@Cart4W": "3.149", "@Cart5L": "1", "@Cart5W": "3.417", "@Cart6L": "1", "@Cart6W": "3.286", "@StationID": "BL12", "@TrainNumber": "218", "@updateTime": "2020-07-13 20:32:17"}, "BL13": {"@CID": "2", "@Cart1L": "1", "@Cart1W": "3.344", "@Cart2L": "1", "@Cart2W": "3.476", "@Cart3L": "1", "@Cart3W": "3.359", "@Cart4L": "1", "@Cart4W": "3.193", "@Cart5L": "1", "@Cart5W": "3.457", "@Cart6L": "1", "@Cart6W": "3.286", "@StationID": "BL13", "@TrainNumber": "218", "@updateTime": "2020-07-13 20:33:46"}, "BL14": {"@CID": "2", "@Cart1L": "1", "@Cart1W": "3.32", "@Cart2L": "1", "@Cart2W": "3.461", "@Cart3L": "1", "@Cart3W": "3.398", "@Cart4L": "1", "@Cart4W": "3.305", "@Cart5L": "1", "@Cart5W": "3.476", "@Cart6L": "1", "@Cart6W": "3.295", "@StationID": "BL14", "@TrainNumber": "218", "@updateTime": "2020-07-13 20:35:47"}, "BL15": {"@CID": "2", "@Cart1L": "1", "@Cart1W": "3.286", "@Cart2L": "1", "@Cart2W": "3.476", "@Cart3L": "1", "@Cart3W": "3.461", "@Cart4L": "1", "@Cart4W": "3.315", "@Cart5L": "1", "@Cart5W": "3.491", "@Cart6L": "1", "@Cart6W": "3.295", "@StationID": "BL15", "@TrainNumber": "218", "@updateTime": "2020-07-13 20:37:25"}, "BL17": {"@CID": "2", "@Cart1L": "1", "@Cart1W": "3.256", "@Cart2L": "1", "@Cart2W": "3.452", "@Cart3L": "1", "@Cart3W": "3.437", "@Cart4L": "1", "@Cart4W": "3.266", "@Cart5L": "1", "@Cart5W": "3.491", "@Cart6L": "1", "@Cart6W": "3.237", "@StationID": "BL17", "@TrainNumber": "218", "@updateTime": "2020-07-13 20:40:45"}, "BL18": {"@CID": "2", "@Cart1L": "1", "@Cart1W": "3.247", "@Cart2L": "1", "@Cart2W": "3.452", "@Cart3L": "1", "@Cart3W": "3.417", "@Cart4L": "1", "@Cart4W": "3.237", "@Cart5L": "1", "@Cart5W": "3.427", "@Cart6L": "1", "@Cart6W": "3.212", "@StationID": "BL18", "@TrainNumber": "218", "@updateTime": "2020-07-13 20:42:29"}, "BL19": {"@CID": "2", "@Cart1L": "1", "@Cart1W": "3.247", "@Cart2L": "1", "@Cart2W": "3.447", "@Cart3L": "1", "@Cart3W": "3.413", "@Cart4L": "1", "@Cart4W": "3.188", "@Cart5L": "1", "@Cart5W": "3.373", "@Cart6L": "1", "@Cart6W": "3.207", "@StationID": "BL19", "@TrainNumber": "218", "@updateTime": "2020-07-13 20:44:18"}, "BL20": {"@CID": "2", "@Cart1L": "1", "@Cart1W": "3.266", "@Cart2L": "1", "@Cart2W": "3.413", "@Cart3L": "1", "@Cart3W": "3.383", "@Cart4L": "1", "@Cart4W": "3.159", "@Cart5L": "1", "@Cart5W": "3.344", "@Cart6L": "1", "@Cart6W": "3.203", "@StationID": "BL20", "@TrainNumber": "218", "@updateTime": "2020-07-13 20:45:55"}, "BL21": {"@CID": "2", "@Cart1L": "1", "@Cart1W": "3.281", "@Cart2L": "1", "@Cart2W": "3.359", "@Cart3L": "1", "@Cart3W": "3.325", "@Cart4L": "1", "@Cart4W": "3.129", "@Cart5L": "1", "@Cart5W": "3.31", "@Cart6L": "1", "@Cart6W": "3.178", "@StationID": "BL21", "@TrainNumber": "218", "@updateTime": "2020-07-13 20:48:15"}, "BL22": {"@CID": "2", "@Cart1L": "1", "@Cart1W": "3.207", "@Cart2L": "1", "@Cart2W": "3.266", "@Cart3L": "1", "@Cart3W": "3.256", "@Cart4L": "1", "@Cart4W": "3.066", "@Cart5L": "1", "@Cart5W": "3.271", "@Cart6L": "1", "@Cart6W": "3.168", "@StationID": "BL22", "@TrainNumber": "218", "@updateTime": "2020-07-13 20:50:33"}}