{"BL01": {"@CID": "2", "@Cart1L": "1", "@Cart1W": "3.354", "@Cart2L": "1", "@Cart2W": "3.29", "@Cart3L": "1", "@Cart3W": "3.188", "@Cart4L": "1", "@Cart4W": "3.457", "@Cart5L": "1", "@Cart5W": "3.364", "@Cart6L": "1", "@Cart6W": "3.334", "@StationID": "BL01", "@TrainNumber": "206", "@updateTime": "2020-07-16 08:05:05"}, "BL02": {"@CID": "2", "@Cart1L": "1", "@Cart1W": "3.457", "@Cart2L": "1", "@Cart2W": "3.427", "@Cart3L": "1", "@Cart3W": "3.442", "@Cart4L": "1", "@Cart4W": "3.73", "@Cart5L": "1", "@Cart5W": "3.583", "@Cart6L": "1", "@Cart6W": "3.447", "@StationID": "BL02", "@TrainNumber": "206", "@updateTime": "2020-07-16 08:07:57"}, "BL03": {"@CID": "2", "@Cart1L": "1", "@Cart1W": "3.579", "@Cart2L": "1", "@Cart2W": "3.54", "@Cart3L": "1", "@Cart3W": "3.657", "@Cart4L": "2", "@Cart4W": "3.969", "@Cart5L": "1", "@Cart5W": "3.793", "@Cart6L": "1", "@Cart6W": "3.608", "@StationID": "BL03", "@TrainNumber": "206", "@updateTime": "2020-07-16 08:09:53"}, "BL04": {"@CID": "2", "@Cart1L": "2", "@Cart1W": "3.989", "@Cart2L": "2", "@Cart2W": "4.125", "@Cart3L": "3", "@Cart3W": "4.384", "@Cart4L": "3", "@Cart4W": "4.487", "@Cart5L": "3", "@Cart5W": "4.272", "@Cart6L": "2", "@Cart6W": "4.003", "@StationID": "BL04", "@TrainNumber": "206", "@updateTime": "2020-07-16 08:12:16"}, "BL05": {"@CID": "2", "@Cart1L": "2", "@Cart1W": "4.008", "@Cart2L": "3", "@Cart2W": "4.296", "@Cart3L": "3", "@Cart3W": "4.58", "@Cart4L": "3", "@Cart4W": "4.643", "@Cart5L": "3", "@Cart5W": "4.36", "@Cart6L": "2", "@Cart6W": "4.125", "@StationID": "BL05", "@TrainNumber": "206", "@updateTime": "2020-07-16 08:14:58"}, "BL06": {"@CID": "2", "@Cart1L": "2", "@Cart1W": "4.194", "@Cart2L": "3", "@Cart2W": "4.423", "@Cart3L": "4", "@Cart3W": "4.736", "@Cart4L": "4", "@Cart4W": "4.77", "@Cart5L": "3", "@Cart5W": "4.511", "@Cart6L": "2", "@Cart6W": "4.194", "@StationID": "BL06", "@TrainNumber": "206", "@updateTime": "2020-07-16 08:17:01"}, "BL07": {"@CID": "2", "@Cart1L": "3", "@Cart1W": "4.409", "@Cart2L": "3", "@Cart2W": "4.56", "@Cart3L": "4", "@Cart3W": "4.794", "@Cart4L": "4", "@Cart4W": "4.721", "@Cart5L": "3", "@Cart5W": "4.599", "@Cart6L": "3", "@Cart6W": "4.37", "@StationID": "BL07", "@TrainNumber": "206", "@updateTime": "2020-07-16 08:18:36"}, "BL08": {"@CID": "2", "@Cart1L": "3", "@Cart1W": "4.545", "@Cart2L": "4", "@Cart2W": "4.692", "@Cart3L": "4", "@Cart3W": "4.702", "@Cart4L": "4", "@Cart4W": "4.726", "@Cart5L": "4", "@Cart5W": "4.711", "@Cart6L": "3", "@Cart6W": "4.565", "@StationID": "BL08", "@TrainNumber": "206", "@updateTime": "2020-07-16 08:20:48"}, "BL09": {"@CID": "2", "@Cart1L": "4", "@Cart1W": "4.697", "@Cart2L": "4", "@Cart2W": "4.78", "@Cart3L": "4", "@Cart3W": "4.819", "@Cart4L": "4", "@Cart4W": "4.829", "@Cart5L": "4", "@Cart5W": "4.726", "@Cart6L": "4", "@Cart6W": "4.653", "@StationID": "BL09", "@TrainNumber": "206", "@updateTime": "2020-07-16 08:22:40"}, "BL10": {"@CID": "2", "@Cart1L": "4", "@Cart1W": "4.751", "@Cart2L": "4", "@Cart2W": "4.877", "@Cart3L": "4", "@Cart3W": "4.931", "@Cart4L": "4", "@Cart4W": "4.834", "@Cart5L": "4", "@Cart5W": "4.731", "@Cart6L": "4", "@Cart6W": "4.721", "@StationID": "BL10", "@TrainNumber": "206", "@updateTime": "2020-07-16 08:26:14"}, "BL11": {"@CID": "2", "@Cart1L": "3", "@Cart1W": "4.375", "@Cart2L": "3", "@Cart2W": "4.389", "@Cart3L": "3", "@Cart3W": "4.448", "@Cart4L": "3", "@Cart4W": "4.379", "@Cart5L": "3", "@Cart5W": "4.409", "@Cart6L": "3", "@Cart6W": "4.438", "@StationID": "BL11", "@TrainNumber": "206", "@updateTime": "2020-07-16 08:28:38"}, "BL12": {"@CID": "2", "@Cart1L": "2", "@Cart1W": "3.984", "@Cart2L": "3", "@Cart2W": "4.316", "@Cart3L": "3", "@Cart3W": "4.34", "@Cart4L": "3", "@Cart4W": "4.384", "@Cart5L": "3", "@Cart5W": "4.423", "@Cart6L": "3", "@Cart6W": "4.262", "@StationID": "BL12", "@TrainNumber": "206", "@updateTime": "2020-07-16 08:31:09"}, "BL13": {"@CID": "2", "@Cart1L": "2", "@Cart1W": "3.847", "@Cart2L": "3", "@Cart2W": "4.36", "@Cart3L": "3", "@Cart3W": "4.389", "@Cart4L": "3", "@Cart4W": "4.438", "@Cart5L": "3", "@Cart5W": "4.399", "@Cart6L": "3", "@Cart6W": "4.394", "@StationID": "BL13", "@TrainNumber": "206", "@updateTime": "2020-07-16 08:32:53"}, "BL14": {"@CID": "2", "@Cart1L": "2", "@Cart1W": "4.248", "@Cart2L": "3", "@Cart2W": "4.56", "@Cart3L": "3", "@Cart3W": "4.55", "@Cart4L": "4", "@Cart4W": "4.731", "@Cart5L": "3", "@Cart5W": "4.575", "@Cart6L": "3", "@Cart6W": "4.448", "@StationID": "BL14", "@TrainNumber": "206", "@updateTime": "2020-07-16 08:34:52"}, "BL15": {"@CID": "2", "@Cart1L": "2", "@Cart1W": "4.135", "@Cart2L": "3", "@Cart2W": "4.594", "@Cart3L": "3", "@Cart3W": "4.482", "@Cart4L": "3", "@Cart4W": "4.477", "@Cart5L": "3", "@Cart5W": "4.355", "@Cart6L": "3", "@Cart6W": "4.306", "@StationID": "BL15", "@TrainNumber": "206", "@updateTime": "2020-07-16 08:37:08"}, "BL16": {"@CID": "2", "@Cart1L": "2", "@Cart1W": "4.038", "@Cart2L": "3", "@Cart2W": "4.506", "@Cart3L": "3", "@Cart3W": "4.472", "@Cart4L": "3", "@Cart4W": "4.34", "@Cart5L": "3", "@Cart5W": "4.326", "@Cart6L": "2", "@Cart6W": "4.174", "@StationID": "BL16", "@TrainNumber": "206", "@updateTime": "2020-07-16 08:38:41"}, "BL17": {"@CID": "2", "@Cart1L": "2", "@Cart1W": "3.969", "@Cart2L": "3", "@Cart2W": "4.409", "@Cart3L": "3", "@Cart3W": "4.292", "@Cart4L": "2", "@Cart4W": "4.096", "@Cart5L": "2", "@Cart5W": "4.145", "@Cart6L": "2", "@Cart6W": "4.013", "@StationID": "BL17", "@TrainNumber": "206", "@updateTime": "2020-07-16 08:40:20"}, "BL18": {"@CID": "2", "@Cart1L": "2", "@Cart1W": "3.818", "@Cart2L": "2", "@Cart2W": "4.086", "@Cart3L": "1", "@Cart3W": "3.789", "@Cart4L": "1", "@Cart4W": "3.554", "@Cart5L": "1", "@Cart5W": "3.725", "@Cart6L": "1", "@Cart6W": "3.632", "@StationID": "BL18", "@TrainNumber": "206", "@updateTime": "2020-07-16 08:42:11"}, "BL19": {"@CID": "2", "@Cart1L": "1", "@Cart1W": "3.637", "@Cart2L": "2", "@Cart2W": "3.969", "@Cart3L": "1", "@Cart3W": "3.652", "@Cart4L": "1", "@Cart4W": "3.422", "@Cart5L": "1", "@Cart5W": "3.535", "@Cart6L": "1", "@Cart6W": "3.564", "@StationID": "BL19", "@TrainNumber": "206", "@updateTime": "2020-07-16 08:44:09"}, "BL20": {"@CID": "2", "@Cart1L": "1", "@Cart1W": "3.53", "@Cart2L": "2", "@Cart2W": "3.901", "@Cart3L": "1", "@Cart3W": "3.535", "@Cart4L": "1", "@Cart4W": "3.364", "@Cart5L": "1", "@Cart5W": "3.496", "@Cart6L": "1", "@Cart6W": "3.515", "@StationID": "BL20", "@TrainNumber": "206", "@updateTime": "2020-07-16 08:45:41"}, "BL21": {"@CID": "2", "@Cart1L": "1", "@Cart1W": "3.466", "@Cart2L": "1", "@Cart2W": "3.696", "@Cart3L": "1", "@Cart3W": "3.388", "@Cart4L": "1", "@Cart4W": "3.33", "@Cart5L": "1", "@Cart5W": "3.403", "@Cart6L": "1", "@Cart6W": "3.432", "@StationID": "BL21", "@TrainNumber": "206", "@updateTime": "2020-07-16 08:47:44"}, "BL22": {"@CID": "2", "@Cart1L": "1", "@Cart1W": "3.247", "@Cart2L": "1", "@Cart2W": "3.549", "@Cart3L": "1", "@Cart3W": "3.286", "@Cart4L": "1", "@Cart4W": "3.207", "@Cart5L": "1", "@Cart5W": "3.266", "@Cart6L": "1", "@Cart6W": "3.295", "@StationID": "BL22", "@TrainNumber": "206", "@updateTime": "2020-07-16 08:51:01"}}