{"BL01": {"@CID": "2", "@Cart1L": "1", "@Cart1W": "3.242", "@Cart2L": "1", "@Cart2W": "3.164", "@Cart3L": "1", "@Cart3W": "3.193", "@Cart4L": "1", "@Cart4W": "3.124", "@Cart5L": "1", "@Cart5W": "3.168", "@Cart6L": "1", "@Cart6W": "3.144", "@StationID": "BL01", "@TrainNumber": "203", "@updateTime": "2020-07-16 09:24:53"}, "BL02": {"@CID": "2", "@Cart1L": "1", "@Cart1W": "3.237", "@Cart2L": "1", "@Cart2W": "3.217", "@Cart3L": "1", "@Cart3W": "3.237", "@Cart4L": "1", "@Cart4W": "3.266", "@Cart5L": "1", "@Cart5W": "3.281", "@Cart6L": "1", "@Cart6W": "3.286", "@StationID": "BL02", "@TrainNumber": "203", "@updateTime": "2020-07-16 09:27:59"}, "BL03": {"@CID": "2", "@Cart1L": "1", "@Cart1W": "3.271", "@Cart2L": "1", "@Cart2W": "3.33", "@Cart3L": "1", "@Cart3W": "3.305", "@Cart4L": "1", "@Cart4W": "3.422", "@Cart5L": "1", "@Cart5W": "3.378", "@Cart6L": "1", "@Cart6W": "3.359", "@StationID": "BL03", "@TrainNumber": "203", "@updateTime": "2020-07-16 09:30:04"}, "BL04": {"@CID": "2", "@Cart1L": "1", "@Cart1W": "3.466", "@Cart2L": "1", "@Cart2W": "3.588", "@Cart3L": "1", "@Cart3W": "3.603", "@Cart4L": "1", "@Cart4W": "3.632", "@Cart5L": "1", "@Cart5W": "3.593", "@Cart6L": "1", "@Cart6W": "3.54", "@StationID": "BL04", "@TrainNumber": "203", "@updateTime": "2020-07-16 09:32:23"}, "BL05": {"@CID": "2", "@Cart1L": "1", "@Cart1W": "3.564", "@Cart2L": "1", "@Cart2W": "3.696", "@Cart3L": "1", "@Cart3W": "3.706", "@Cart4L": "1", "@Cart4W": "3.74", "@Cart5L": "1", "@Cart5W": "3.642", "@Cart6L": "1", "@Cart6W": "3.623", "@StationID": "BL05", "@TrainNumber": "203", "@updateTime": "2020-07-16 09:35:12"}, "BL06": {"@CID": "2", "@Cart1L": "1", "@Cart1W": "3.662", "@Cart2L": "2", "@Cart2W": "3.842", "@Cart3L": "2", "@Cart3W": "3.95", "@Cart4L": "2", "@Cart4W": "3.955", "@Cart5L": "1", "@Cart5W": "3.759", "@Cart6L": "1", "@Cart6W": "3.74", "@StationID": "BL06", "@TrainNumber": "203", "@updateTime": "2020-07-16 09:37:24"}, "BL07": {"@CID": "1", "@Cart1L": "1", "@Cart1W": "3.164", "@Cart2L": "1", "@Cart2W": "3.33", "@Cart3L": "1", "@Cart3W": "3.281", "@Cart4L": "1", "@Cart4W": "3.325", "@Cart5L": "1", "@Cart5W": "3.164", "@Cart6L": "1", "@Cart6W": "3.159", "@StationID": "BL07", "@TrainNumber": "221", "@updateTime": "2020-07-16 10:01:45"}, "BL08": {"@CID": "2", "@Cart1L": "2", "@Cart1W": "3.862", "@Cart2L": "2", "@Cart2W": "4.091", "@Cart3L": "2", "@Cart3W": "4.14", "@Cart4L": "2", "@Cart4W": "4.15", "@Cart5L": "2", "@Cart5W": "4.135", "@Cart6L": "2", "@Cart6W": "3.876", "@StationID": "BL08", "@TrainNumber": "203", "@updateTime": "2020-07-16 09:41:24"}, "BL09": {"@CID": "2", "@Cart1L": "2", "@Cart1W": "3.901", "@Cart2L": "3", "@Cart2W": "4.252", "@Cart3L": "2", "@Cart3W": "4.233", "@Cart4L": "2", "@Cart4W": "4.16", "@Cart5L": "3", "@Cart5W": "4.287", "@Cart6L": "2", "@Cart6W": "3.964", "@StationID": "BL09", "@TrainNumber": "203", "@updateTime": "2020-07-16 09:43:14"}, "BL10": {"@CID": "2", "@Cart1L": "2", "@Cart1W": "3.935", "@Cart2L": "3", "@Cart2W": "4.345", "@Cart3L": "3", "@Cart3W": "4.321", "@Cart4L": "2", "@Cart4W": "4.243", "@Cart5L": "3", "@Cart5W": "4.423", "@Cart6L": "2", "@Cart6W": "4.018", "@StationID": "BL10", "@TrainNumber": "203", "@updateTime": "2020-07-16 09:46:57"}, "BL11": {"@CID": "2", "@Cart1L": "1", "@Cart1W": "3.784", "@Cart2L": "2", "@Cart2W": "4.165", "@Cart3L": "2", "@Cart3W": "4.121", "@Cart4L": "2", "@Cart4W": "4.038", "@Cart5L": "2", "@Cart5W": "4.179", "@Cart6L": "2", "@Cart6W": "3.867", "@StationID": "BL11", "@TrainNumber": "203", "@updateTime": "2020-07-16 09:49:32"}, "BL12": {"@CID": "2", "@Cart1L": "1", "@Cart1W": "3.793", "@Cart2L": "2", "@Cart2W": "4.179", "@Cart3L": "2", "@Cart3W": "4.125", "@Cart4L": "2", "@Cart4W": "3.891", "@Cart5L": "2", "@Cart5W": "3.93", "@Cart6L": "1", "@Cart6W": "3.706", "@StationID": "BL12", "@TrainNumber": "203", "@updateTime": "2020-07-16 09:52:13"}, "BL13": {"@CID": "2", "@Cart1L": "1", "@Cart1W": "3.784", "@Cart2L": "2", "@Cart2W": "4.145", "@Cart3L": "2", "@Cart3W": "4.096", "@Cart4L": "2", "@Cart4W": "3.872", "@Cart5L": "2", "@Cart5W": "3.857", "@Cart6L": "1", "@Cart6W": "3.671", "@StationID": "BL13", "@TrainNumber": "203", "@updateTime": "2020-07-16 09:53:43"}, "BL14": {"@CID": "2", "@Cart1L": "1", "@Cart1W": "3.774", "@Cart2L": "2", "@Cart2W": "4.213", "@Cart3L": "2", "@Cart3W": "4.243", "@Cart4L": "2", "@Cart4W": "4.091", "@Cart5L": "2", "@Cart5W": "3.979", "@Cart6L": "1", "@Cart6W": "3.666", "@StationID": "BL14", "@TrainNumber": "203", "@updateTime": "2020-07-16 09:55:45"}, "BL15": {"@CID": "2", "@Cart1L": "1", "@Cart1W": "3.671", "@Cart2L": "2", "@Cart2W": "4.042", "@Cart3L": "2", "@Cart3W": "4.125", "@Cart4L": "2", "@Cart4W": "3.935", "@Cart5L": "2", "@Cart5W": "3.94", "@Cart6L": "1", "@Cart6W": "3.632", "@StationID": "BL15", "@TrainNumber": "203", "@updateTime": "2020-07-16 09:57:58"}, "BL16": {"@CID": "2", "@Cart1L": "1", "@Cart1W": "3.583", "@Cart2L": "2", "@Cart2W": "3.989", "@Cart3L": "2", "@Cart3W": "3.95", "@Cart4L": "1", "@Cart4W": "3.769", "@Cart5L": "2", "@Cart5W": "3.837", "@Cart6L": "1", "@Cart6W": "3.549", "@StationID": "BL16", "@TrainNumber": "203", "@updateTime": "2020-07-16 09:59:29"}, "BL17": {"@CID": "2", "@Cart1L": "1", "@Cart1W": "3.481", "@Cart2L": "1", "@Cart2W": "3.764", "@Cart3L": "2", "@Cart3W": "3.833", "@Cart4L": "1", "@Cart4W": "3.652", "@Cart5L": "1", "@Cart5W": "3.71", "@Cart6L": "1", "@Cart6W": "3.53", "@StationID": "BL17", "@TrainNumber": "203", "@updateTime": "2020-07-16 10:01:05"}, "BL18": {"@CID": "2", "@Cart1L": "1", "@Cart1W": "3.403", "@Cart2L": "1", "@Cart2W": "3.569", "@Cart3L": "1", "@Cart3W": "3.476", "@Cart4L": "1", "@Cart4W": "3.359", "@Cart5L": "1", "@Cart5W": "3.447", "@Cart6L": "1", "@Cart6W": "3.349", "@StationID": "BL18", "@TrainNumber": "203", "@updateTime": "2020-07-16 10:02:52"}, "BL19": {"@CID": "2", "@Cart1L": "1", "@Cart1W": "3.325", "@Cart2L": "1", "@Cart2W": "3.466", "@Cart3L": "1", "@Cart3W": "3.31", "@Cart4L": "1", "@Cart4W": "3.217", "@Cart5L": "1", "@Cart5W": "3.271", "@Cart6L": "1", "@Cart6W": "3.305", "@StationID": "BL19", "@TrainNumber": "203", "@updateTime": "2020-07-16 10:04:46"}, "BL20": {"@CID": "2", "@Cart1L": "1", "@Cart1W": "3.295", "@Cart2L": "1", "@Cart2W": "3.432", "@Cart3L": "1", "@Cart3W": "3.295", "@Cart4L": "1", "@Cart4W": "3.168", "@Cart5L": "1", "@Cart5W": "3.251", "@Cart6L": "1", "@Cart6W": "3.266", "@StationID": "BL20", "@TrainNumber": "203", "@updateTime": "2020-07-16 10:06:25"}, "BL21": {"@CID": "2", "@Cart1L": "1", "@Cart1W": "3.29", "@Cart2L": "1", "@Cart2W": "3.364", "@Cart3L": "1", "@Cart3W": "3.237", "@Cart4L": "1", "@Cart4W": "3.129", "@Cart5L": "1", "@Cart5W": "3.188", "@Cart6L": "1", "@Cart6W": "3.217", "@StationID": "BL21", "@TrainNumber": "203", "@updateTime": "2020-07-16 10:08:41"}, "BL22": {"@CID": "2", "@Cart1L": "1", "@Cart1W": "3.232", "@Cart2L": "1", "@Cart2W": "3.266", "@Cart3L": "1", "@Cart3W": "3.178", "@Cart4L": "1", "@Cart4W": "3.061", "@Cart5L": "1", "@Cart5W": "3.154", "@Cart6L": "1", "@Cart6W": "3.198", "@StationID": "BL22", "@TrainNumber": "203", "@updateTime": "2020-07-16 10:11:01"}}