{"BL01": {"@CID": "2", "@Cart1L": "1", "@Cart1W": "3.129", "@Cart2L": "1", "@Cart2W": "3.056", "@Cart3L": "1", "@Cart3W": "3.002", "@Cart4L": "1", "@Cart4W": "3.11", "@Cart5L": "1", "@Cart5W": "2.993", "@Cart6L": "1", "@Cart6W": "3.09", "@StationID": "BL01", "@TrainNumber": "206", "@updateTime": "2020-07-16 09:48:49"}, "BL02": {"@CID": "2", "@Cart1L": "1", "@Cart1W": "3.188", "@Cart2L": "1", "@Cart2W": "3.081", "@Cart3L": "1", "@Cart3W": "3.066", "@Cart4L": "1", "@Cart4W": "3.286", "@Cart5L": "1", "@Cart5W": "3.12", "@Cart6L": "1", "@Cart6W": "3.178", "@StationID": "BL02", "@TrainNumber": "206", "@updateTime": "2020-07-16 09:51:54"}, "BL03": {"@CID": "2", "@Cart1L": "1", "@Cart1W": "3.212", "@Cart2L": "1", "@Cart2W": "3.159", "@Cart3L": "1", "@Cart3W": "3.178", "@Cart4L": "1", "@Cart4W": "3.383", "@Cart5L": "1", "@Cart5W": "3.198", "@Cart6L": "1", "@Cart6W": "3.247", "@StationID": "BL03", "@TrainNumber": "206", "@updateTime": "2020-07-16 09:53:58"}, "BL04": {"@CID": "2", "@Cart1L": "1", "@Cart1W": "3.427", "@Cart2L": "1", "@Cart2W": "3.398", "@Cart3L": "1", "@Cart3W": "3.437", "@Cart4L": "1", "@Cart4W": "3.535", "@Cart5L": "1", "@Cart5W": "3.325", "@Cart6L": "1", "@Cart6W": "3.339", "@StationID": "BL04", "@TrainNumber": "206", "@updateTime": "2020-07-16 09:56:14"}, "BL05": {"@CID": "2", "@Cart1L": "1", "@Cart1W": "3.461", "@Cart2L": "1", "@Cart2W": "3.54", "@Cart3L": "1", "@Cart3W": "3.564", "@Cart4L": "1", "@Cart4W": "3.598", "@Cart5L": "1", "@Cart5W": "3.344", "@Cart6L": "1", "@Cart6W": "3.422", "@StationID": "BL05", "@TrainNumber": "206", "@updateTime": "2020-07-16 09:59:06"}, "BL06": {"@CID": "2", "@Cart1L": "1", "@Cart1W": "3.53", "@Cart2L": "1", "@Cart2W": "3.603", "@Cart3L": "1", "@Cart3W": "3.691", "@Cart4L": "1", "@Cart4W": "3.764", "@Cart5L": "1", "@Cart5W": "3.393", "@Cart6L": "1", "@Cart6W": "3.403", "@StationID": "BL06", "@TrainNumber": "206", "@updateTime": "2020-07-16 10:01:16"}, "BL07": {"@CID": "2", "@Cart1L": "1", "@Cart1W": "3.676", "@Cart2L": "1", "@Cart2W": "3.696", "@Cart3L": "1", "@Cart3W": "3.759", "@Cart4L": "1", "@Cart4W": "3.789", "@Cart5L": "1", "@Cart5W": "3.559", "@Cart6L": "1", "@Cart6W": "3.549", "@StationID": "BL07", "@TrainNumber": "206", "@updateTime": "2020-07-16 10:02:47"}, "BL08": {"@CID": "2", "@Cart1L": "1", "@Cart1W": "3.71", "@Cart2L": "1", "@Cart2W": "3.74", "@Cart3L": "1", "@Cart3W": "3.74", "@Cart4L": "2", "@Cart4W": "3.842", "@Cart5L": "1", "@Cart5W": "3.657", "@Cart6L": "1", "@Cart6W": "3.642", "@StationID": "BL08", "@TrainNumber": "206", "@updateTime": "2020-07-16 10:05:09"}, "BL09": {"@CID": "2", "@Cart1L": "1", "@Cart1W": "3.754", "@Cart2L": "1", "@Cart2W": "3.774", "@Cart3L": "2", "@Cart3W": "3.803", "@Cart4L": "2", "@Cart4W": "3.891", "@Cart5L": "2", "@Cart5W": "3.813", "@Cart6L": "1", "@Cart6W": "3.676", "@StationID": "BL09", "@TrainNumber": "206", "@updateTime": "2020-07-16 10:06:52"}, "BL10": {"@CID": "2", "@Cart1L": "1", "@Cart1W": "3.793", "@Cart2L": "2", "@Cart2W": "3.911", "@Cart3L": "2", "@Cart3W": "3.842", "@Cart4L": "2", "@Cart4W": "4.057", "@Cart5L": "2", "@Cart5W": "3.964", "@Cart6L": "1", "@Cart6W": "3.706", "@StationID": "BL10", "@TrainNumber": "206", "@updateTime": "2020-07-16 10:10:33"}, "BL11": {"@CID": "2", "@Cart1L": "1", "@Cart1W": "3.774", "@Cart2L": "2", "@Cart2W": "3.916", "@Cart3L": "2", "@Cart3W": "3.837", "@Cart4L": "2", "@Cart4W": "3.95", "@Cart5L": "2", "@Cart5W": "3.857", "@Cart6L": "1", "@Cart6W": "3.701", "@StationID": "BL11", "@TrainNumber": "206", "@updateTime": "2020-07-16 10:13:11"}, "BL12": {"@CID": "2", "@Cart1L": "1", "@Cart1W": "3.764", "@Cart2L": "2", "@Cart2W": "3.92", "@Cart3L": "2", "@Cart3W": "3.857", "@Cart4L": "1", "@Cart4W": "3.735", "@Cart5L": "1", "@Cart5W": "3.657", "@Cart6L": "1", "@Cart6W": "3.515", "@StationID": "BL12", "@TrainNumber": "206", "@updateTime": "2020-07-16 10:15:51"}, "BL13": {"@CID": "2", "@Cart1L": "1", "@Cart1W": "3.74", "@Cart2L": "2", "@Cart2W": "4.028", "@Cart3L": "2", "@Cart3W": "3.891", "@Cart4L": "1", "@Cart4W": "3.701", "@Cart5L": "1", "@Cart5W": "3.637", "@Cart6L": "1", "@Cart6W": "3.437", "@StationID": "BL13", "@TrainNumber": "206", "@updateTime": "2020-07-16 10:17:22"}, "BL14": {"@CID": "2", "@Cart1L": "1", "@Cart1W": "3.696", "@Cart2L": "2", "@Cart2W": "4.023", "@Cart3L": "2", "@Cart3W": "4.086", "@Cart4L": "2", "@Cart4W": "3.901", "@Cart5L": "1", "@Cart5W": "3.686", "@Cart6L": "1", "@Cart6W": "3.447", "@StationID": "BL14", "@TrainNumber": "206", "@updateTime": "2020-07-16 10:19:28"}, "BL15": {"@CID": "2", "@Cart1L": "1", "@Cart1W": "3.618", "@Cart2L": "2", "@Cart2W": "4.008", "@Cart3L": "2", "@Cart3W": "3.989", "@Cart4L": "2", "@Cart4W": "3.808", "@Cart5L": "1", "@Cart5W": "3.671", "@Cart6L": "1", "@Cart6W": "3.325", "@StationID": "BL15", "@TrainNumber": "206", "@updateTime": "2020-07-16 10:21:40"}, "BL16": {"@CID": "2", "@Cart1L": "1", "@Cart1W": "3.496", "@Cart2L": "2", "@Cart2W": "3.842", "@Cart3L": "1", "@Cart3W": "3.764", "@Cart4L": "1", "@Cart4W": "3.706", "@Cart5L": "1", "@Cart5W": "3.579", "@Cart6L": "1", "@Cart6W": "3.286", "@StationID": "BL16", "@TrainNumber": "206", "@updateTime": "2020-07-16 10:23:10"}, "BL17": {"@CID": "2", "@Cart1L": "1", "@Cart1W": "3.408", "@Cart2L": "1", "@Cart2W": "3.696", "@Cart3L": "1", "@Cart3W": "3.618", "@Cart4L": "1", "@Cart4W": "3.657", "@Cart5L": "1", "@Cart5W": "3.442", "@Cart6L": "1", "@Cart6W": "3.247", "@StationID": "BL17", "@TrainNumber": "206", "@updateTime": "2020-07-16 10:24:48"}, "BL18": {"@CID": "2", "@Cart1L": "1", "@Cart1W": "3.388", "@Cart2L": "1", "@Cart2W": "3.647", "@Cart3L": "1", "@Cart3W": "3.564", "@Cart4L": "1", "@Cart4W": "3.613", "@Cart5L": "1", "@Cart5W": "3.393", "@Cart6L": "1", "@Cart6W": "3.217", "@StationID": "BL18", "@TrainNumber": "206", "@updateTime": "2020-07-16 10:26:03"}, "BL19": {"@CID": "2", "@Cart1L": "1", "@Cart1W": "3.266", "@Cart2L": "1", "@Cart2W": "3.422", "@Cart3L": "1", "@Cart3W": "3.237", "@Cart4L": "1", "@Cart4W": "3.31", "@Cart5L": "1", "@Cart5W": "3.242", "@Cart6L": "1", "@Cart6W": "3.115", "@StationID": "BL19", "@TrainNumber": "206", "@updateTime": "2020-07-16 10:28:03"}, "BL20": {"@CID": "2", "@Cart1L": "1", "@Cart1W": "3.256", "@Cart2L": "1", "@Cart2W": "3.334", "@Cart3L": "1", "@Cart3W": "3.056", "@Cart4L": "1", "@Cart4W": "3.237", "@Cart5L": "1", "@Cart5W": "3.227", "@Cart6L": "1", "@Cart6W": "3.056", "@StationID": "BL20", "@TrainNumber": "206", "@updateTime": "2020-07-16 10:29:44"}, "BL21": {"@CID": "2", "@Cart1L": "1", "@Cart1W": "3.237", "@Cart2L": "1", "@Cart2W": "3.3", "@Cart3L": "1", "@Cart3W": "3.046", "@Cart4L": "1", "@Cart4W": "3.222", "@Cart5L": "1", "@Cart5W": "3.139", "@Cart6L": "1", "@Cart6W": "3.061", "@StationID": "BL21", "@TrainNumber": "206", "@updateTime": "2020-07-16 10:32:25"}, "BL22": {"@CID": "2", "@Cart1L": "1", "@Cart1W": "3.159", "@Cart2L": "1", "@Cart2W": "3.266", "@Cart3L": "1", "@Cart3W": "2.997", "@Cart4L": "1", "@Cart4W": "3.173", "@Cart5L": "1", "@Cart5W": "3.12", "@Cart6L": "1", "@Cart6W": "3.081", "@StationID": "BL22", "@TrainNumber": "206", "@updateTime": "2020-07-16 10:34:53"}}