{"BL01": {"@CID": "2", "@Cart1L": "1", "@Cart1W": "3.061", "@Cart2L": "1", "@Cart2W": "3.27", "@Cart3L": "1", "@Cart3W": "2.95", "@Cart4L": "1", "@Cart4W": "3.093", "@Cart5L": "1", "@Cart5W": "3.175", "@Cart6L": "1", "@Cart6W": "3.06", "@StationID": "BL01", "@TrainNumber": "213", "@updateTime": "2020-07-16 11:05:01"}, "BL02": {"@CID": "2", "@Cart1L": "1", "@Cart1W": "3.145", "@Cart2L": "1", "@Cart2W": "3.296", "@Cart3L": "1", "@Cart3W": "2.987", "@Cart4L": "1", "@Cart4W": "3.257", "@Cart5L": "1", "@Cart5W": "3.181", "@Cart6L": "1", "@Cart6W": "3.089", "@StationID": "BL02", "@TrainNumber": "213", "@updateTime": "2020-07-16 11:08:05"}, "BL03": {"@CID": "2", "@Cart1L": "1", "@Cart1W": "3.218", "@Cart2L": "1", "@Cart2W": "3.359", "@Cart3L": "1", "@Cart3W": "3.074", "@Cart4L": "1", "@Cart4W": "3.346", "@Cart5L": "1", "@Cart5W": "3.264", "@Cart6L": "1", "@Cart6W": "3.136", "@StationID": "BL03", "@TrainNumber": "213", "@updateTime": "2020-07-16 11:10:07"}, "BL04": {"@CID": "2", "@Cart1L": "1", "@Cart1W": "3.287", "@Cart2L": "1", "@Cart2W": "3.558", "@Cart3L": "1", "@Cart3W": "3.254", "@Cart4L": "1", "@Cart4W": "3.534", "@Cart5L": "1", "@Cart5W": "3.38", "@Cart6L": "1", "@Cart6W": "3.179", "@StationID": "BL04", "@TrainNumber": "213", "@updateTime": "2020-07-16 11:12:20"}, "BL05": {"@CID": "2", "@Cart1L": "1", "@Cart1W": "3.376", "@Cart2L": "1", "@Cart2W": "3.65", "@Cart3L": "1", "@Cart3W": "3.383", "@Cart4L": "1", "@Cart4W": "3.701", "@Cart5L": "1", "@Cart5W": "3.435", "@Cart6L": "1", "@Cart6W": "3.213", "@StationID": "BL05", "@TrainNumber": "213", "@updateTime": "2020-07-16 11:15:11"}, "BL06": {"@CID": "2", "@Cart1L": "1", "@Cart1W": "3.483", "@Cart2L": "1", "@Cart2W": "3.711", "@Cart3L": "1", "@Cart3W": "3.579", "@Cart4L": "2", "@Cart4W": "3.836", "@Cart5L": "1", "@Cart5W": "3.532", "@Cart6L": "1", "@Cart6W": "3.259", "@StationID": "BL06", "@TrainNumber": "213", "@updateTime": "2020-07-16 11:17:22"}, "BL07": {"@CID": "2", "@Cart1L": "1", "@Cart1W": "3.574", "@Cart2L": "1", "@Cart2W": "3.782", "@Cart3L": "1", "@Cart3W": "3.696", "@Cart4L": "2", "@Cart4W": "3.895", "@Cart5L": "1", "@Cart5W": "3.606", "@Cart6L": "1", "@Cart6W": "3.375", "@StationID": "BL07", "@TrainNumber": "213", "@updateTime": "2020-07-16 11:18:57"}, "BL08": {"@CID": "2", "@Cart1L": "1", "@Cart1W": "3.705", "@Cart2L": "2", "@Cart2W": "3.877", "@Cart3L": "1", "@Cart3W": "3.696", "@Cart4L": "2", "@Cart4W": "3.921", "@Cart5L": "1", "@Cart5W": "3.693", "@Cart6L": "1", "@Cart6W": "3.479", "@StationID": "BL08", "@TrainNumber": "213", "@updateTime": "2020-07-16 11:21:17"}, "BL09": {"@CID": "2", "@Cart1L": "1", "@Cart1W": "3.754", "@Cart2L": "2", "@Cart2W": "3.9", "@Cart3L": "1", "@Cart3W": "3.711", "@Cart4L": "2", "@Cart4W": "4.015", "@Cart5L": "1", "@Cart5W": "3.742", "@Cart6L": "1", "@Cart6W": "3.49", "@StationID": "BL09", "@TrainNumber": "213", "@updateTime": "2020-07-16 11:23:02"}, "BL10": {"@CID": "2", "@Cart1L": "1", "@Cart1W": "3.797", "@Cart2L": "2", "@Cart2W": "3.976", "@Cart3L": "1", "@Cart3W": "3.787", "@Cart4L": "2", "@Cart4W": "4.1", "@Cart5L": "2", "@Cart5W": "3.869", "@Cart6L": "1", "@Cart6W": "3.568", "@StationID": "BL10", "@TrainNumber": "213", "@updateTime": "2020-07-16 11:26:44"}, "BL11": {"@CID": "2", "@Cart1L": "1", "@Cart1W": "3.681", "@Cart2L": "2", "@Cart2W": "3.973", "@Cart3L": "1", "@Cart3W": "3.761", "@Cart4L": "2", "@Cart4W": "4.011", "@Cart5L": "2", "@Cart5W": "3.955", "@Cart6L": "1", "@Cart6W": "3.584", "@StationID": "BL11", "@TrainNumber": "213", "@updateTime": "2020-07-16 11:29:17"}, "BL12": {"@CID": "2", "@Cart1L": "1", "@Cart1W": "3.573", "@Cart2L": "2", "@Cart2W": "3.992", "@Cart3L": "2", "@Cart3W": "3.921", "@Cart4L": "1", "@Cart4W": "3.745", "@Cart5L": "1", "@Cart5W": "3.776", "@Cart6L": "1", "@Cart6W": "3.51", "@StationID": "BL12", "@TrainNumber": "213", "@updateTime": "2020-07-16 11:31:54"}, "BL13": {"@CID": "2", "@Cart1L": "1", "@Cart1W": "3.606", "@Cart2L": "2", "@Cart2W": "4.086", "@Cart3L": "2", "@Cart3W": "4.018", "@Cart4L": "1", "@Cart4W": "3.749", "@Cart5L": "1", "@Cart5W": "3.768", "@Cart6L": "1", "@Cart6W": "3.477", "@StationID": "BL13", "@TrainNumber": "213", "@updateTime": "2020-07-16 11:33:26"}, "BL14": {"@CID": "2", "@Cart1L": "1", "@Cart1W": "3.62", "@Cart2L": "2", "@Cart2W": "4.138", "@Cart3L": "3", "@Cart3W": "4.273", "@Cart4L": "2", "@Cart4W": "3.914", "@Cart5L": "1", "@Cart5W": "3.769", "@Cart6L": "1", "@Cart6W": "3.496", "@StationID": "BL14", "@TrainNumber": "213", "@updateTime": "2020-07-16 11:35:36"}, "BL15": {"@CID": "2", "@Cart1L": "1", "@Cart1W": "3.626", "@Cart2L": "2", "@Cart2W": "4.116", "@Cart3L": "2", "@Cart3W": "4.205", "@Cart4L": "2", "@Cart4W": "3.906", "@Cart5L": "1", "@Cart5W": "3.795", "@Cart6L": "1", "@Cart6W": "3.417", "@StationID": "BL15", "@TrainNumber": "213", "@updateTime": "2020-07-16 11:37:51"}, "BL16": {"@CID": "2", "@Cart1L": "1", "@Cart1W": "3.548", "@Cart2L": "2", "@Cart2W": "3.911", "@Cart3L": "2", "@Cart3W": "3.98", "@Cart4L": "2", "@Cart4W": "3.803", "@Cart5L": "1", "@Cart5W": "3.69", "@Cart6L": "1", "@Cart6W": "3.35", "@StationID": "BL16", "@TrainNumber": "213", "@updateTime": "2020-07-16 11:39:26"}, "BL17": {"@CID": "2", "@Cart1L": "1", "@Cart1W": "3.475", "@Cart2L": "2", "@Cart2W": "3.82", "@Cart3L": "1", "@Cart3W": "3.762", "@Cart4L": "1", "@Cart4W": "3.69", "@Cart5L": "1", "@Cart5W": "3.646", "@Cart6L": "1", "@Cart6W": "3.302", "@StationID": "BL17", "@TrainNumber": "213", "@updateTime": "2020-07-16 11:41:07"}, "BL18": {"@CID": "2", "@Cart1L": "1", "@Cart1W": "3.28", "@Cart2L": "1", "@Cart2W": "3.585", "@Cart3L": "1", "@Cart3W": "3.384", "@Cart4L": "1", "@Cart4W": "3.387", "@Cart5L": "1", "@Cart5W": "3.497", "@Cart6L": "1", "@Cart6W": "3.205", "@StationID": "BL18", "@TrainNumber": "213", "@updateTime": "2020-07-16 11:42:52"}, "BL19": {"@CID": "2", "@Cart1L": "1", "@Cart1W": "3.181", "@Cart2L": "1", "@Cart2W": "3.492", "@Cart3L": "1", "@Cart3W": "3.187", "@Cart4L": "1", "@Cart4W": "3.292", "@Cart5L": "1", "@Cart5W": "3.415", "@Cart6L": "1", "@Cart6W": "3.155", "@StationID": "BL19", "@TrainNumber": "213", "@updateTime": "2020-07-16 11:44:43"}, "BL20": {"@CID": "2", "@Cart1L": "1", "@Cart1W": "3.113", "@Cart2L": "1", "@Cart2W": "3.452", "@Cart3L": "1", "@Cart3W": "3.098", "@Cart4L": "1", "@Cart4W": "3.228", "@Cart5L": "1", "@Cart5W": "3.356", "@Cart6L": "1", "@Cart6W": "3.1", "@StationID": "BL20", "@TrainNumber": "213", "@updateTime": "2020-07-16 11:46:23"}, "BL21": {"@CID": "2", "@Cart1L": "1", "@Cart1W": "3.143", "@Cart2L": "1", "@Cart2W": "3.427", "@Cart3L": "1", "@Cart3W": "3.157", "@Cart4L": "1", "@Cart4W": "3.228", "@Cart5L": "1", "@Cart5W": "3.295", "@Cart6L": "1", "@Cart6W": "3.079", "@StationID": "BL21", "@TrainNumber": "213", "@updateTime": "2020-07-16 11:48:46"}, "BL22": {"@CID": "2", "@Cart1L": "1", "@Cart1W": "3.141", "@Cart2L": "1", "@Cart2W": "3.411", "@Cart3L": "1", "@Cart3W": "3.154", "@Cart4L": "1", "@Cart4W": "3.183", "@Cart5L": "1", "@Cart5W": "3.244", "@Cart6L": "1", "@Cart6W": "3.088", "@StationID": "BL22", "@TrainNumber": "213", "@updateTime": "2020-07-16 11:51:14"}}