{"BL23": {"@CID": "1", "@Cart1L": "1", "@Cart1W": "3.178", "@Cart2L": "1", "@Cart2W": "3.178", "@Cart3L": "1", "@Cart3W": "3.032", "@Cart4L": "1", "@Cart4W": "3.149", "@Cart5L": "1", "@Cart5W": "3.33", "@Cart6L": "1", "@Cart6W": "2.983", "@StationID": "BL23", "@TrainNumber": "219", "@updateTime": "2020-07-18 08:54:22"}, "BL22": {"@CID": "1", "@Cart1L": "1", "@Cart1W": "3.188", "@Cart2L": "1", "@Cart2W": "3.334", "@Cart3L": "1", "@Cart3W": "3.041", "@Cart4L": "1", "@Cart4W": "3.188", "@Cart5L": "1", "@Cart5W": "3.334", "@Cart6L": "1", "@Cart6W": "2.983", "@StationID": "BL22", "@TrainNumber": "219", "@updateTime": "2020-07-18 08:56:28"}, "BL21": {"@CID": "1", "@Cart1L": "1", "@Cart1W": "3.276", "@Cart2L": "1", "@Cart2W": "3.422", "@Cart3L": "1", "@Cart3W": "3.139", "@Cart4L": "1", "@Cart4W": "3.237", "@Cart5L": "1", "@Cart5W": "3.325", "@Cart6L": "1", "@Cart6W": "3.022", "@StationID": "BL21", "@TrainNumber": "219", "@updateTime": "2020-07-18 08:58:50"}, "BL20": {"@CID": "1", "@Cart1L": "1", "@Cart1W": "3.325", "@Cart2L": "1", "@Cart2W": "3.481", "@Cart3L": "1", "@Cart3W": "3.198", "@Cart4L": "1", "@Cart4W": "3.256", "@Cart5L": "1", "@Cart5W": "3.33", "@Cart6L": "1", "@Cart6W": "3.041", "@StationID": "BL20", "@TrainNumber": "219", "@updateTime": "2020-07-18 09:01:11"}, "BL19": {"@CID": "1", "@Cart1L": "1", "@Cart1W": "3.325", "@Cart2L": "1", "@Cart2W": "3.481", "@Cart3L": "1", "@Cart3W": "3.29", "@Cart4L": "1", "@Cart4W": "3.344", "@Cart5L": "1", "@Cart5W": "3.354", "@Cart6L": "1", "@Cart6W": "3.041", "@StationID": "BL19", "@TrainNumber": "219", "@updateTime": "2020-07-18 09:02:49"}, "BL18": {"@CID": "1", "@Cart1L": "1", "@Cart1W": "3.344", "@Cart2L": "1", "@Cart2W": "3.461", "@Cart3L": "1", "@Cart3W": "3.33", "@Cart4L": "1", "@Cart4W": "3.432", "@Cart5L": "1", "@Cart5W": "3.422", "@Cart6L": "1", "@Cart6W": "3.041", "@StationID": "BL18", "@TrainNumber": "219", "@updateTime": "2020-07-18 09:04:33"}, "BL17": {"@CID": "1", "@Cart1L": "1", "@Cart1W": "3.344", "@Cart2L": "1", "@Cart2W": "3.461", "@Cart3L": "1", "@Cart3W": "3.344", "@Cart4L": "1", "@Cart4W": "3.466", "@Cart5L": "1", "@Cart5W": "3.432", "@Cart6L": "1", "@Cart6W": "3.041", "@StationID": "BL17", "@TrainNumber": "219", "@updateTime": "2020-07-18 09:06:13"}, "BL16": {"@CID": "1", "@Cart1L": "1", "@Cart1W": "3.344", "@Cart2L": "1", "@Cart2W": "3.461", "@Cart3L": "1", "@Cart3W": "3.349", "@Cart4L": "1", "@Cart4W": "3.466", "@Cart5L": "1", "@Cart5W": "3.452", "@Cart6L": "1", "@Cart6W": "3.081", "@StationID": "BL16", "@TrainNumber": "219", "@updateTime": "2020-07-18 09:07:51"}, "BL15": {"@CID": "1", "@Cart1L": "1", "@Cart1W": "3.364", "@Cart2L": "1", "@Cart2W": "3.452", "@Cart3L": "1", "@Cart3W": "3.432", "@Cart4L": "1", "@Cart4W": "3.588", "@Cart5L": "1", "@Cart5W": "3.52", "@Cart6L": "1", "@Cart6W": "3.124", "@StationID": "BL15", "@TrainNumber": "219", "@updateTime": "2020-07-18 09:09:37"}, "BL13": {"@CID": "1", "@Cart1L": "1", "@Cart1W": "3.378", "@Cart2L": "1", "@Cart2W": "3.432", "@Cart3L": "1", "@Cart3W": "3.53", "@Cart4L": "1", "@Cart4W": "3.588", "@Cart5L": "1", "@Cart5W": "3.491", "@Cart6L": "1", "@Cart6W": "3.159", "@StationID": "BL13", "@TrainNumber": "219", "@updateTime": "2020-07-18 09:13:38"}, "BL12": {"@CID": "1", "@Cart1L": "1", "@Cart1W": "3.354", "@Cart2L": "1", "@Cart2W": "3.364", "@Cart3L": "1", "@Cart3W": "3.393", "@Cart4L": "1", "@Cart4W": "3.452", "@Cart5L": "1", "@Cart5W": "3.461", "@Cart6L": "1", "@Cart6W": "3.193", "@StationID": "BL12", "@TrainNumber": "219", "@updateTime": "2020-07-18 09:15:21"}, "BL11": {"@CID": "1", "@Cart1L": "1", "@Cart1W": "3.373", "@Cart2L": "1", "@Cart2W": "3.393", "@Cart3L": "1", "@Cart3W": "3.442", "@Cart4L": "1", "@Cart4W": "3.349", "@Cart5L": "1", "@Cart5W": "3.422", "@Cart6L": "1", "@Cart6W": "3.188", "@StationID": "BL11", "@TrainNumber": "219", "@updateTime": "2020-07-18 09:18:08"}, "BL10": {"@CID": "1", "@Cart1L": "1", "@Cart1W": "3.369", "@Cart2L": "1", "@Cart2W": "3.457", "@Cart3L": "1", "@Cart3W": "3.422", "@Cart4L": "1", "@Cart4W": "3.295", "@Cart5L": "1", "@Cart5W": "3.417", "@Cart6L": "1", "@Cart6W": "3.198", "@StationID": "BL10", "@TrainNumber": "219", "@updateTime": "2020-07-18 09:20:17"}, "BL09": {"@CID": "1", "@Cart1L": "1", "@Cart1W": "3.32", "@Cart2L": "1", "@Cart2W": "3.388", "@Cart3L": "1", "@Cart3W": "3.413", "@Cart4L": "1", "@Cart4W": "3.354", "@Cart5L": "1", "@Cart5W": "3.413", "@Cart6L": "1", "@Cart6W": "3.207", "@StationID": "BL09", "@TrainNumber": "219", "@updateTime": "2020-07-18 09:24:00"}, "BL08": {"@CID": "1", "@Cart1L": "1", "@Cart1W": "3.315", "@Cart2L": "1", "@Cart2W": "3.334", "@Cart3L": "1", "@Cart3W": "3.403", "@Cart4L": "1", "@Cart4W": "3.393", "@Cart5L": "1", "@Cart5W": "3.427", "@Cart6L": "1", "@Cart6W": "3.203", "@StationID": "BL08", "@TrainNumber": "219", "@updateTime": "2020-07-18 09:25:40"}, "BL07": {"@CID": "1", "@Cart1L": "1", "@Cart1W": "3.286", "@Cart2L": "1", "@Cart2W": "3.364", "@Cart3L": "1", "@Cart3W": "3.403", "@Cart4L": "1", "@Cart4W": "3.408", "@Cart5L": "1", "@Cart5W": "3.383", "@Cart6L": "1", "@Cart6W": "3.198", "@StationID": "BL07", "@TrainNumber": "219", "@updateTime": "2020-07-18 09:27:59"}, "BL06": {"@CID": "1", "@Cart1L": "1", "@Cart1W": "3.247", "@Cart2L": "1", "@Cart2W": "3.281", "@Cart3L": "1", "@Cart3W": "3.32", "@Cart4L": "1", "@Cart4W": "3.378", "@Cart5L": "1", "@Cart5W": "3.32", "@Cart6L": "1", "@Cart6W": "3.193", "@StationID": "BL06", "@TrainNumber": "219", "@updateTime": "2020-07-18 09:29:33"}, "BL05": {"@CID": "1", "@Cart1L": "1", "@Cart1W": "3.217", "@Cart2L": "1", "@Cart2W": "3.227", "@Cart3L": "1", "@Cart3W": "3.266", "@Cart4L": "1", "@Cart4W": "3.305", "@Cart5L": "1", "@Cart5W": "3.295", "@Cart6L": "1", "@Cart6W": "3.139", "@StationID": "BL05", "@TrainNumber": "219", "@updateTime": "2020-07-18 09:31:46"}, "BL04": {"@CID": "1", "@Cart1L": "1", "@Cart1W": "3.207", "@Cart2L": "1", "@Cart2W": "3.256", "@Cart3L": "1", "@Cart3W": "3.286", "@Cart4L": "1", "@Cart4W": "3.295", "@Cart5L": "1", "@Cart5W": "3.29", "@Cart6L": "1", "@Cart6W": "3.149", "@StationID": "BL04", "@TrainNumber": "219", "@updateTime": "2020-07-18 09:34:43"}, "BL03": {"@CID": "1", "@Cart1L": "1", "@Cart1W": "3.207", "@Cart2L": "1", "@Cart2W": "3.173", "@Cart3L": "1", "@Cart3W": "3.261", "@Cart4L": "1", "@Cart4W": "3.286", "@Cart5L": "1", "@Cart5W": "3.261", "@Cart6L": "1", "@Cart6W": "3.095", "@StationID": "BL03", "@TrainNumber": "219", "@updateTime": "2020-07-18 09:37:01"}, "BL02": {"@CID": "1", "@Cart1L": "1", "@Cart1W": "3.212", "@Cart2L": "1", "@Cart2W": "3.188", "@Cart3L": "1", "@Cart3W": "3.173", "@Cart4L": "1", "@Cart4W": "3.212", "@Cart5L": "1", "@Cart5W": "3.217", "@Cart6L": "1", "@Cart6W": "3.056", "@StationID": "BL02", "@TrainNumber": "219", "@updateTime": "2020-07-18 09:39:00"}, "BL01": {"@CID": "2", "@Cart1L": "1", "@Cart1W": "3.207", "@Cart2L": "1", "@Cart2W": "3.129", "@Cart3L": "1", "@Cart3W": "3.149", "@Cart4L": "1", "@Cart4W": "3.129", "@Cart5L": "1", "@Cart5W": "3.154", "@Cart6L": "1", "@Cart6W": "3.022", "@StationID": "BL01", "@TrainNumber": "219", "@updateTime": "2020-07-18 09:43:21"}}