{"BL23": {"@CID": "1", "@Cart1L": "1", "@Cart1W": "3.142", "@Cart2L": "1", "@Cart2W": "3.566", "@Cart3L": "1", "@Cart3W": "3.154", "@Cart4L": "1", "@Cart4W": "3.226", "@Cart5L": "1", "@Cart5W": "3.469", "@Cart6L": "1", "@Cart6W": "3.217", "@StationID": "BL23", "@TrainNumber": "224", "@updateTime": "2020-07-15 08:16:25"}, "BL22": {"@CID": "1", "@Cart1L": "1", "@Cart1W": "3.147", "@Cart2L": "1", "@Cart2W": "3.57", "@Cart3L": "1", "@Cart3W": "3.369", "@Cart4L": "1", "@Cart4W": "3.3", "@Cart5L": "1", "@Cart5W": "3.555", "@Cart6L": "1", "@Cart6W": "3.283", "@StationID": "BL22", "@TrainNumber": "224", "@updateTime": "2020-07-15 08:18:48"}, "BL21": {"@CID": "1", "@Cart1L": "1", "@Cart1W": "3.23", "@Cart2L": "1", "@Cart2W": "3.594", "@Cart3L": "1", "@Cart3W": "3.516", "@Cart4L": "1", "@Cart4W": "3.36", "@Cart5L": "1", "@Cart5W": "3.609", "@Cart6L": "1", "@Cart6W": "3.399", "@StationID": "BL21", "@TrainNumber": "224", "@updateTime": "2020-07-15 08:20:59"}, "BL20": {"@CID": "1", "@Cart1L": "1", "@Cart1W": "3.293", "@Cart2L": "1", "@Cart2W": "3.651", "@Cart3L": "1", "@Cart3W": "3.736", "@Cart4L": "1", "@Cart4W": "3.534", "@Cart5L": "1", "@Cart5W": "3.575", "@Cart6L": "1", "@Cart6W": "3.443", "@StationID": "BL20", "@TrainNumber": "224", "@updateTime": "2020-07-15 08:23:20"}, "BL19": {"@CID": "1", "@Cart1L": "1", "@Cart1W": "3.362", "@Cart2L": "1", "@Cart2W": "3.727", "@Cart3L": "2", "@Cart3W": "3.91", "@Cart4L": "1", "@Cart4W": "3.738", "@Cart5L": "1", "@Cart5W": "3.712", "@Cart6L": "1", "@Cart6W": "3.449", "@StationID": "BL19", "@TrainNumber": "224", "@updateTime": "2020-07-15 08:25:03"}, "BL18": {"@CID": "1", "@Cart1L": "1", "@Cart1W": "3.436", "@Cart2L": "1", "@Cart2W": "3.781", "@Cart3L": "2", "@Cart3W": "3.938", "@Cart4L": "1", "@Cart4W": "3.784", "@Cart5L": "2", "@Cart5W": "3.805", "@Cart6L": "1", "@Cart6W": "3.536", "@StationID": "BL18", "@TrainNumber": "224", "@updateTime": "2020-07-15 08:26:57"}, "BL17": {"@CID": "1", "@Cart1L": "1", "@Cart1W": "3.433", "@Cart2L": "1", "@Cart2W": "3.778", "@Cart3L": "2", "@Cart3W": "3.931", "@Cart4L": "1", "@Cart4W": "3.798", "@Cart5L": "2", "@Cart5W": "3.805", "@Cart6L": "1", "@Cart6W": "3.536", "@StationID": "BL17", "@TrainNumber": "224", "@updateTime": "2020-07-15 08:28:39"}, "BL16": {"@CID": "1", "@Cart1L": "1", "@Cart1W": "3.433", "@Cart2L": "1", "@Cart2W": "3.777", "@Cart3L": "2", "@Cart3W": "3.93", "@Cart4L": "2", "@Cart4W": "3.826", "@Cart5L": "2", "@Cart5W": "3.827", "@Cart6L": "1", "@Cart6W": "3.535", "@StationID": "BL16", "@TrainNumber": "224", "@updateTime": "2020-07-15 08:30:16"}, "BL15": {"@CID": "1", "@Cart1L": "1", "@Cart1W": "3.435", "@Cart2L": "1", "@Cart2W": "3.779", "@Cart3L": "2", "@Cart3W": "3.934", "@Cart4L": "1", "@Cart4W": "3.784", "@Cart5L": "2", "@Cart5W": "3.869", "@Cart6L": "1", "@Cart6W": "3.541", "@StationID": "BL15", "@TrainNumber": "224", "@updateTime": "2020-07-15 08:31:59"}, "BL14": {"@CID": "1", "@Cart1L": "1", "@Cart1W": "3.453", "@Cart2L": "2", "@Cart2W": "3.847", "@Cart3L": "2", "@Cart3W": "3.888", "@Cart4L": "1", "@Cart4W": "3.759", "@Cart5L": "2", "@Cart5W": "3.885", "@Cart6L": "1", "@Cart6W": "3.539", "@StationID": "BL14", "@TrainNumber": "224", "@updateTime": "2020-07-15 08:34:14"}, "BL13": {"@CID": "1", "@Cart1L": "1", "@Cart1W": "3.455", "@Cart2L": "1", "@Cart2W": "3.762", "@Cart3L": "1", "@Cart3W": "3.747", "@Cart4L": "1", "@Cart4W": "3.699", "@Cart5L": "1", "@Cart5W": "3.783", "@Cart6L": "1", "@Cart6W": "3.541", "@StationID": "BL13", "@TrainNumber": "224", "@updateTime": "2020-07-15 08:36:05"}, "BL12": {"@CID": "1", "@Cart1L": "1", "@Cart1W": "3.331", "@Cart2L": "1", "@Cart2W": "3.679", "@Cart3L": "1", "@Cart3W": "3.631", "@Cart4L": "1", "@Cart4W": "3.596", "@Cart5L": "1", "@Cart5W": "3.65", "@Cart6L": "1", "@Cart6W": "3.5", "@StationID": "BL12", "@TrainNumber": "224", "@updateTime": "2020-07-15 08:37:58"}, "BL11": {"@CID": "1", "@Cart1L": "1", "@Cart1W": "3.322", "@Cart2L": "1", "@Cart2W": "3.642", "@Cart3L": "1", "@Cart3W": "3.614", "@Cart4L": "1", "@Cart4W": "3.547", "@Cart5L": "1", "@Cart5W": "3.625", "@Cart6L": "1", "@Cart6W": "3.463", "@StationID": "BL11", "@TrainNumber": "224", "@updateTime": "2020-07-15 08:40:23"}, "BL10": {"@CID": "1", "@Cart1L": "1", "@Cart1W": "3.226", "@Cart2L": "1", "@Cart2W": "3.567", "@Cart3L": "1", "@Cart3W": "3.587", "@Cart4L": "1", "@Cart4W": "3.518", "@Cart5L": "1", "@Cart5W": "3.59", "@Cart6L": "1", "@Cart6W": "3.419", "@StationID": "BL10", "@TrainNumber": "224", "@updateTime": "2020-07-15 08:42:26"}, "BL09": {"@CID": "1", "@Cart1L": "1", "@Cart1W": "3.19", "@Cart2L": "1", "@Cart2W": "3.5", "@Cart3L": "1", "@Cart3W": "3.552", "@Cart4L": "1", "@Cart4W": "3.491", "@Cart5L": "1", "@Cart5W": "3.531", "@Cart6L": "1", "@Cart6W": "3.348", "@StationID": "BL09", "@TrainNumber": "224", "@updateTime": "2020-07-15 08:46:02"}, "BL08": {"@CID": "1", "@Cart1L": "1", "@Cart1W": "3.188", "@Cart2L": "1", "@Cart2W": "3.498", "@Cart3L": "1", "@Cart3W": "3.551", "@Cart4L": "1", "@Cart4W": "3.456", "@Cart5L": "1", "@Cart5W": "3.47", "@Cart6L": "1", "@Cart6W": "3.342", "@StationID": "BL08", "@TrainNumber": "224", "@updateTime": "2020-07-15 08:47:37"}, "BL07": {"@CID": "1", "@Cart1L": "1", "@Cart1W": "3.07", "@Cart2L": "1", "@Cart2W": "3.471", "@Cart3L": "1", "@Cart3W": "3.438", "@Cart4L": "1", "@Cart4W": "3.435", "@Cart5L": "1", "@Cart5W": "3.443", "@Cart6L": "1", "@Cart6W": "3.266", "@StationID": "BL07", "@TrainNumber": "224", "@updateTime": "2020-07-15 08:49:44"}, "BL06": {"@CID": "1", "@Cart1L": "1", "@Cart1W": "3.014", "@Cart2L": "1", "@Cart2W": "3.419", "@Cart3L": "1", "@Cart3W": "3.313", "@Cart4L": "1", "@Cart4W": "3.387", "@Cart5L": "1", "@Cart5W": "3.386", "@Cart6L": "1", "@Cart6W": "3.247", "@StationID": "BL06", "@TrainNumber": "224", "@updateTime": "2020-07-15 08:51:11"}, "BL05": {"@CID": "1", "@Cart1L": "1", "@Cart1W": "3.012", "@Cart2L": "1", "@Cart2W": "3.378", "@Cart3L": "1", "@Cart3W": "3.238", "@Cart4L": "1", "@Cart4W": "3.317", "@Cart5L": "1", "@Cart5W": "3.382", "@Cart6L": "1", "@Cart6W": "3.215", "@StationID": "BL05", "@TrainNumber": "224", "@updateTime": "2020-07-15 08:53:17"}, "BL04": {"@CID": "1", "@Cart1L": "1", "@Cart1W": "3.011", "@Cart2L": "1", "@Cart2W": "3.311", "@Cart3L": "1", "@Cart3W": "3.178", "@Cart4L": "1", "@Cart4W": "3.251", "@Cart5L": "1", "@Cart5W": "3.379", "@Cart6L": "1", "@Cart6W": "3.2", "@StationID": "BL04", "@TrainNumber": "224", "@updateTime": "2020-07-15 08:55:55"}, "BL03": {"@CID": "1", "@Cart1L": "1", "@Cart1W": "2.995", "@Cart2L": "1", "@Cart2W": "3.309", "@Cart3L": "1", "@Cart3W": "3.153", "@Cart4L": "1", "@Cart4W": "3.202", "@Cart5L": "1", "@Cart5W": "3.371", "@Cart6L": "1", "@Cart6W": "3.197", "@StationID": "BL03", "@TrainNumber": "224", "@updateTime": "2020-07-15 08:58:09"}, "BL02": {"@CID": "1", "@Cart1L": "1", "@Cart1W": "2.995", "@Cart2L": "1", "@Cart2W": "3.304", "@Cart3L": "1", "@Cart3W": "3.113", "@Cart4L": "1", "@Cart4W": "3.111", "@Cart5L": "1", "@Cart5W": "3.374", "@Cart6L": "1", "@Cart6W": "3.185", "@StationID": "BL02", "@TrainNumber": "224", "@updateTime": "2020-07-15 09:00:09"}, "BL01": {"@CID": "2", "@Cart1L": "1", "@Cart1W": "2.98", "@Cart2L": "1", "@Cart2W": "3.274", "@Cart3L": "1", "@Cart3W": "3.053", "@Cart4L": "1", "@Cart4W": "3.073", "@Cart5L": "1", "@Cart5W": "3.304", "@Cart6L": "1", "@Cart6W": "3.193", "@StationID": "BL01", "@TrainNumber": "224", "@updateTime": "2020-07-15 09:04:18"}}