{"BL23": {"@CID": "1", "@Cart1L": "1", "@Cart1W": "3.159", "@Cart2L": "1", "@Cart2W": "3.305", "@Cart3L": "1", "@Cart3W": "3.339", "@Cart4L": "1", "@Cart4W": "3.237", "@Cart5L": "1", "@Cart5W": "3.5", "@Cart6L": "1", "@Cart6W": "3.266", "@StationID": "BL23", "@TrainNumber": "218", "@updateTime": "2020-07-13 17:30:14"}, "BL22": {"@CID": "1", "@Cart1L": "1", "@Cart1W": "3.198", "@Cart2L": "1", "@Cart2W": "3.359", "@Cart3L": "1", "@Cart3W": "3.398", "@Cart4L": "1", "@Cart4W": "3.237", "@Cart5L": "1", "@Cart5W": "3.525", "@Cart6L": "1", "@Cart6W": "3.315", "@StationID": "BL22", "@TrainNumber": "218", "@updateTime": "2020-07-13 17:32:22"}, "BL21": {"@CID": "1", "@Cart1L": "1", "@Cart1W": "3.388", "@Cart2L": "1", "@Cart2W": "3.505", "@Cart3L": "1", "@Cart3W": "3.544", "@Cart4L": "1", "@Cart4W": "3.305", "@Cart5L": "1", "@Cart5W": "3.554", "@Cart6L": "1", "@Cart6W": "3.369", "@StationID": "BL21", "@TrainNumber": "218", "@updateTime": "2020-07-13 17:34:37"}, "BL20": {"@CID": "1", "@Cart1L": "1", "@Cart1W": "3.452", "@Cart2L": "1", "@Cart2W": "3.544", "@Cart3L": "1", "@Cart3W": "3.681", "@Cart4L": "1", "@Cart4W": "3.373", "@Cart5L": "1", "@Cart5W": "3.583", "@Cart6L": "1", "@Cart6W": "3.432", "@StationID": "BL20", "@TrainNumber": "218", "@updateTime": "2020-07-13 17:36:40"}, "BL19": {"@CID": "1", "@Cart1L": "1", "@Cart1W": "3.452", "@Cart2L": "1", "@Cart2W": "3.608", "@Cart3L": "1", "@Cart3W": "3.769", "@Cart4L": "1", "@Cart4W": "3.505", "@Cart5L": "1", "@Cart5W": "3.642", "@Cart6L": "1", "@Cart6W": "3.486", "@StationID": "BL19", "@TrainNumber": "218", "@updateTime": "2020-07-13 17:38:16"}, "BL18": {"@CID": "1", "@Cart1L": "1", "@Cart1W": "3.598", "@Cart2L": "2", "@Cart2W": "3.852", "@Cart3L": "2", "@Cart3W": "4.067", "@Cart4L": "2", "@Cart4W": "4.057", "@Cart5L": "2", "@Cart5W": "4.209", "@Cart6L": "2", "@Cart6W": "3.813", "@StationID": "BL18", "@TrainNumber": "218", "@updateTime": "2020-07-13 17:40:19"}, "BL17": {"@CID": "1", "@Cart1L": "1", "@Cart1W": "3.676", "@Cart2L": "2", "@Cart2W": "3.989", "@Cart3L": "2", "@Cart3W": "4.228", "@Cart4L": "3", "@Cart4W": "4.282", "@Cart5L": "3", "@Cart5W": "4.453", "@Cart6L": "2", "@Cart6W": "3.969", "@StationID": "BL17", "@TrainNumber": "218", "@updateTime": "2020-07-13 17:42:07"}, "BL16": {"@CID": "1", "@Cart1L": "2", "@Cart1W": "3.823", "@Cart2L": "2", "@Cart2W": "4.238", "@Cart3L": "3", "@Cart3W": "4.482", "@Cart4L": "3", "@Cart4W": "4.418", "@Cart5L": "4", "@Cart5W": "4.692", "@Cart6L": "2", "@Cart6W": "4.194", "@StationID": "BL16", "@TrainNumber": "218", "@updateTime": "2020-07-13 17:43:57"}, "BL15": {"@CID": "1", "@Cart1L": "2", "@Cart1W": "3.837", "@Cart2L": "2", "@Cart2W": "4.243", "@Cart3L": "3", "@Cart3W": "4.526", "@Cart4L": "3", "@Cart4W": "4.477", "@Cart5L": "4", "@Cart5W": "4.697", "@Cart6L": "2", "@Cart6W": "4.233", "@StationID": "BL15", "@TrainNumber": "218", "@updateTime": "2020-07-13 17:45:04"}, "BL14": {"@CID": "1", "@Cart1L": "2", "@Cart1W": "3.959", "@Cart2L": "2", "@Cart2W": "4.228", "@Cart3L": "3", "@Cart3W": "4.296", "@Cart4L": "3", "@Cart4W": "4.365", "@Cart5L": "3", "@Cart5W": "4.516", "@Cart6L": "3", "@Cart6W": "4.36", "@StationID": "BL14", "@TrainNumber": "218", "@updateTime": "2020-07-13 17:47:59"}, "BL13": {"@CID": "1", "@Cart1L": "2", "@Cart1W": "3.999", "@Cart2L": "3", "@Cart2W": "4.272", "@Cart3L": "3", "@Cart3W": "4.516", "@Cart4L": "3", "@Cart4W": "4.34", "@Cart5L": "3", "@Cart5W": "4.521", "@Cart6L": "3", "@Cart6W": "4.389", "@StationID": "BL13", "@TrainNumber": "218", "@updateTime": "2020-07-13 17:49:46"}, "BL12": {"@CID": "1", "@Cart1L": "2", "@Cart1W": "4.145", "@Cart2L": "3", "@Cart2W": "4.321", "@Cart3L": "3", "@Cart3W": "4.389", "@Cart4L": "3", "@Cart4W": "4.379", "@Cart5L": "3", "@Cart5W": "4.487", "@Cart6L": "3", "@Cart6W": "4.418", "@StationID": "BL12", "@TrainNumber": "218", "@updateTime": "2020-07-13 17:51:40"}, "BL11": {"@CID": "1", "@Cart1L": "3", "@Cart1W": "4.531", "@Cart2L": "4", "@Cart2W": "4.702", "@Cart3L": "4", "@Cart3W": "4.702", "@Cart4L": "3", "@Cart4W": "4.585", "@Cart5L": "4", "@Cart5W": "4.746", "@Cart6L": "3", "@Cart6W": "4.648", "@StationID": "BL11", "@TrainNumber": "218", "@updateTime": "2020-07-13 17:54:23"}, "BL10": {"@CID": "1", "@Cart1L": "3", "@Cart1W": "4.57", "@Cart2L": "3", "@Cart2W": "4.604", "@Cart3L": "4", "@Cart3W": "4.721", "@Cart4L": "3", "@Cart4W": "4.638", "@Cart5L": "3", "@Cart5W": "4.633", "@Cart6L": "3", "@Cart6W": "4.614", "@StationID": "BL10", "@TrainNumber": "218", "@updateTime": "2020-07-13 17:56:33"}, "BL09": {"@CID": "1", "@Cart1L": "3", "@Cart1W": "4.506", "@Cart2L": "3", "@Cart2W": "4.448", "@Cart3L": "4", "@Cart3W": "4.711", "@Cart4L": "3", "@Cart4W": "4.545", "@Cart5L": "3", "@Cart5W": "4.394", "@Cart6L": "3", "@Cart6W": "4.526", "@StationID": "BL09", "@TrainNumber": "218", "@updateTime": "2020-07-13 18:00:14"}, "BL08": {"@CID": "1", "@Cart1L": "3", "@Cart1W": "4.311", "@Cart2L": "2", "@Cart2W": "4.213", "@Cart3L": "3", "@Cart3W": "4.555", "@Cart4L": "2", "@Cart4W": "4.243", "@Cart5L": "2", "@Cart5W": "4.238", "@Cart6L": "3", "@Cart6W": "4.345", "@StationID": "BL08", "@TrainNumber": "218", "@updateTime": "2020-07-13 18:02:02"}, "BL07": {"@CID": "1", "@Cart1L": "2", "@Cart1W": "4.086", "@Cart2L": "2", "@Cart2W": "4.018", "@Cart3L": "3", "@Cart3W": "4.404", "@Cart4L": "2", "@Cart4W": "4.072", "@Cart5L": "2", "@Cart5W": "4.067", "@Cart6L": "2", "@Cart6W": "4.189", "@StationID": "BL07", "@TrainNumber": "218", "@updateTime": "2020-07-13 18:04:15"}, "BL06": {"@CID": "1", "@Cart1L": "2", "@Cart1W": "4.008", "@Cart2L": "2", "@Cart2W": "3.857", "@Cart3L": "2", "@Cart3W": "4.238", "@Cart4L": "2", "@Cart4W": "3.994", "@Cart5L": "2", "@Cart5W": "3.945", "@Cart6L": "2", "@Cart6W": "4.033", "@StationID": "BL06", "@TrainNumber": "218", "@updateTime": "2020-07-13 18:05:47"}, "BL05": {"@CID": "1", "@Cart1L": "2", "@Cart1W": "3.876", "@Cart2L": "1", "@Cart2W": "3.784", "@Cart3L": "2", "@Cart3W": "4.111", "@Cart4L": "2", "@Cart4W": "3.974", "@Cart5L": "2", "@Cart5W": "4.086", "@Cart6L": "2", "@Cart6W": "3.93", "@StationID": "BL05", "@TrainNumber": "218", "@updateTime": "2020-07-13 18:08:03"}, "BL04": {"@CID": "1", "@Cart1L": "1", "@Cart1W": "3.735", "@Cart2L": "1", "@Cart2W": "3.588", "@Cart3L": "1", "@Cart3W": "3.662", "@Cart4L": "1", "@Cart4W": "3.642", "@Cart5L": "1", "@Cart5W": "3.696", "@Cart6L": "1", "@Cart6W": "3.749", "@StationID": "BL04", "@TrainNumber": "218", "@updateTime": "2020-07-13 18:10:50"}, "BL03": {"@CID": "1", "@Cart1L": "1", "@Cart1W": "3.535", "@Cart2L": "1", "@Cart2W": "3.461", "@Cart3L": "1", "@Cart3W": "3.471", "@Cart4L": "1", "@Cart4W": "3.491", "@Cart5L": "1", "@Cart5W": "3.403", "@Cart6L": "1", "@Cart6W": "3.51", "@StationID": "BL03", "@TrainNumber": "218", "@updateTime": "2020-07-13 18:13:06"}, "BL02": {"@CID": "1", "@Cart1L": "1", "@Cart1W": "3.393", "@Cart2L": "1", "@Cart2W": "3.232", "@Cart3L": "1", "@Cart3W": "3.33", "@Cart4L": "1", "@Cart4W": "3.217", "@Cart5L": "1", "@Cart5W": "3.237", "@Cart6L": "1", "@Cart6W": "3.349", "@StationID": "BL02", "@TrainNumber": "218", "@updateTime": "2020-07-13 18:15:12"}, "BL01": {"@CID": "2", "@Cart1L": "1", "@Cart1W": "3.198", "@Cart2L": "1", "@Cart2W": "3.173", "@Cart3L": "1", "@Cart3W": "3.286", "@Cart4L": "1", "@Cart4W": "3.173", "@Cart5L": "1", "@Cart5W": "3.266", "@Cart6L": "1", "@Cart6W": "3.242", "@StationID": "BL01", "@TrainNumber": "218", "@updateTime": "2020-07-13 18:19:34"}}