{"BL23": {"@CID": "1", "@Cart1L": "1", "@Cart1W": "3.715", "@Cart2L": "1", "@Cart2W": "3.774", "@Cart3L": "1", "@Cart3W": "3.544", "@Cart4L": "1", "@Cart4W": "3.637", "@Cart5L": "1", "@Cart5W": "3.706", "@Cart6L": "1", "@Cart6W": "3.481", "@StationID": "BL23", "@TrainNumber": "237", "@updateTime": "2020-07-13 17:59:25"}, "BL22": {"@CID": "1", "@Cart1L": "1", "@Cart1W": "3.789", "@Cart2L": "2", "@Cart2W": "3.852", "@Cart3L": "1", "@Cart3W": "3.618", "@Cart4L": "1", "@Cart4W": "3.701", "@Cart5L": "1", "@Cart5W": "3.784", "@Cart6L": "1", "@Cart6W": "3.51", "@StationID": "BL22", "@TrainNumber": "237", "@updateTime": "2020-07-13 18:01:03"}, "BL21": {"@CID": "1", "@Cart1L": "2", "@Cart1W": "4.101", "@Cart2L": "2", "@Cart2W": "4.204", "@Cart3L": "2", "@Cart3W": "3.911", "@Cart4L": "2", "@Cart4W": "3.852", "@Cart5L": "2", "@Cart5W": "3.842", "@Cart6L": "1", "@Cart6W": "3.618", "@StationID": "BL21", "@TrainNumber": "237", "@updateTime": "2020-07-13 18:03:59"}, "BL20": {"@CID": "1", "@Cart1L": "2", "@Cart1W": "4.204", "@Cart2L": "3", "@Cart2W": "4.379", "@Cart3L": "2", "@Cart3W": "4.091", "@Cart4L": "2", "@Cart4W": "3.969", "@Cart5L": "2", "@Cart5W": "3.891", "@Cart6L": "1", "@Cart6W": "3.657", "@StationID": "BL20", "@TrainNumber": "237", "@updateTime": "2020-07-13 18:06:02"}, "BL19": {"@CID": "1", "@Cart1L": "3", "@Cart1W": "4.301", "@Cart2L": "3", "@Cart2W": "4.477", "@Cart3L": "3", "@Cart3W": "4.306", "@Cart4L": "2", "@Cart4W": "4.121", "@Cart5L": "2", "@Cart5W": "3.95", "@Cart6L": "1", "@Cart6W": "3.749", "@StationID": "BL19", "@TrainNumber": "237", "@updateTime": "2020-07-13 18:07:48"}, "BL18": {"@CID": "1", "@Cart1L": "3", "@Cart1W": "4.326", "@Cart2L": "4", "@Cart2W": "4.672", "@Cart3L": "3", "@Cart3W": "4.604", "@Cart4L": "3", "@Cart4W": "4.477", "@Cart5L": "2", "@Cart5W": "4.228", "@Cart6L": "2", "@Cart6W": "3.876", "@StationID": "BL18", "@TrainNumber": "237", "@updateTime": "2020-07-13 18:09:49"}, "BL17": {"@CID": "1", "@Cart1L": "3", "@Cart1W": "4.36", "@Cart2L": "4", "@Cart2W": "4.677", "@Cart3L": "4", "@Cart3W": "4.663", "@Cart4L": "4", "@Cart4W": "4.653", "@Cart5L": "3", "@Cart5W": "4.365", "@Cart6L": "2", "@Cart6W": "3.984", "@StationID": "BL17", "@TrainNumber": "237", "@updateTime": "2020-07-13 18:11:37"}, "BL16": {"@CID": "1", "@Cart1L": "3", "@Cart1W": "4.511", "@Cart2L": "4", "@Cart2W": "4.799", "@Cart3L": "4", "@Cart3W": "4.682", "@Cart4L": "4", "@Cart4W": "4.77", "@Cart5L": "3", "@Cart5W": "4.599", "@Cart6L": "2", "@Cart6W": "4.096", "@StationID": "BL16", "@TrainNumber": "237", "@updateTime": "2020-07-13 18:13:24"}, "BL15": {"@CID": "1", "@Cart1L": "3", "@Cart1W": "4.638", "@Cart2L": "4", "@Cart2W": "4.838", "@Cart3L": "4", "@Cart3W": "4.77", "@Cart4L": "4", "@Cart4W": "4.931", "@Cart5L": "4", "@Cart5W": "4.868", "@Cart6L": "3", "@Cart6W": "4.418", "@StationID": "BL15", "@TrainNumber": "237", "@updateTime": "2020-07-13 18:15:29"}, "BL14": {"@CID": "1", "@Cart1L": "3", "@Cart1W": "4.501", "@Cart2L": "3", "@Cart2W": "4.565", "@Cart3L": "3", "@Cart3W": "4.399", "@Cart4L": "4", "@Cart4W": "4.682", "@Cart5L": "3", "@Cart5W": "4.624", "@Cart6L": "3", "@Cart6W": "4.326", "@StationID": "BL14", "@TrainNumber": "237", "@updateTime": "2020-07-13 18:17:50"}, "BL13": {"@CID": "1", "@Cart1L": "3", "@Cart1W": "4.428", "@Cart2L": "3", "@Cart2W": "4.575", "@Cart3L": "3", "@Cart3W": "4.497", "@Cart4L": "4", "@Cart4W": "4.682", "@Cart5L": "3", "@Cart5W": "4.624", "@Cart6L": "3", "@Cart6W": "4.252", "@StationID": "BL13", "@TrainNumber": "237", "@updateTime": "2020-07-13 18:19:38"}, "BL12": {"@CID": "1", "@Cart1L": "3", "@Cart1W": "4.306", "@Cart2L": "3", "@Cart2W": "4.506", "@Cart3L": "3", "@Cart3W": "4.409", "@Cart4L": "3", "@Cart4W": "4.614", "@Cart5L": "3", "@Cart5W": "4.541", "@Cart6L": "2", "@Cart6W": "4.228", "@StationID": "BL12", "@TrainNumber": "237", "@updateTime": "2020-07-13 18:21:32"}, "BL11": {"@CID": "1", "@Cart1L": "4", "@Cart1W": "4.741", "@Cart2L": "4", "@Cart2W": "4.814", "@Cart3L": "4", "@Cart3W": "4.726", "@Cart4L": "4", "@Cart4W": "4.814", "@Cart5L": "4", "@Cart5W": "4.741", "@Cart6L": "3", "@Cart6W": "4.575", "@StationID": "BL11", "@TrainNumber": "237", "@updateTime": "2020-07-13 18:24:20"}, "BL10": {"@CID": "1", "@Cart1L": "4", "@Cart1W": "4.838", "@Cart2L": "4", "@Cart2W": "4.834", "@Cart3L": "4", "@Cart3W": "4.76", "@Cart4L": "4", "@Cart4W": "4.887", "@Cart5L": "4", "@Cart5W": "4.751", "@Cart6L": "3", "@Cart6W": "4.609", "@StationID": "BL10", "@TrainNumber": "237", "@updateTime": "2020-07-13 18:26:31"}, "BL01": {"@CID": "2", "@Cart1L": "1", "@Cart1W": "3.33", "@Cart2L": "1", "@Cart2W": "3.251", "@Cart3L": "1", "@Cart3W": "3.134", "@Cart4L": "1", "@Cart4W": "3.227", "@Cart5L": "1", "@Cart5W": "3.168", "@Cart6L": "1", "@Cart6W": "3.105", "@StationID": "BL01", "@TrainNumber": "235", "@updateTime": "2020-07-13 18:26:50"}}